{
  "tesseract:recipe_shaped" : {
    "key" : "minecraft:blackstone_wall",
    "tags" : [ "crafting_table" ],
    "map" : {
      "A" : {
        "item" : "minecraft:blackstone",
        "subId" : -1
      }
    },
    "pattern" : [ "AAA", "AAA" ],
    "priority" : 0,
    "result" : {
      "item" : "minecraft:blackstone_wall",
      "count" : 6,
      "blockState" : "minecraft:blackstone_wall[wall_connection_type_east=none,wall_connection_type_north=none,wall_connection_type_south=none,wall_connection_type_west=none,wall_post_bit=false]"
    }
  }
}