{
  "tesseract:recipe_shapeless" : {
    "key" : "minecraft:netherite_ingot",
    "tags" : [ "crafting_table" ],
    "ingredients" : [ {
      "item" : "minecraft:netherite_scrap",
      "subId" : -1
    }, {
      "item" : "minecraft:netherite_scrap",
      "subId" : -1
    }, {
      "item" : "minecraft:netherite_scrap",
      "subId" : -1
    }, {
      "item" : "minecraft:netherite_scrap",
      "subId" : -1
    }, {
      "item" : "minecraft:gold_ingot",
      "subId" : -1
    }, {
      "item" : "minecraft:gold_ingot",
      "subId" : -1
    }, {
      "item" : "minecraft:gold_ingot",
      "subId" : -1
    }, {
      "item" : "minecraft:gold_ingot",
      "subId" : -1
    } ],
    "priority" : 0,
    "result" : {
      "item" : "minecraft:netherite_ingot"
    }
  }
}